nose_connection_report.py
setup.cfg
setup.py
nose_connection_report.egg-info/PKG-INFO
nose_connection_report.egg-info/SOURCES.txt
nose_connection_report.egg-info/dependency_links.txt
nose_connection_report.egg-info/entry_points.txt
nose_connection_report.egg-info/requires.txt
nose_connection_report.egg-info/top_level.txt
nose_connection_report.egg-info/zip-safe