Metadata-Version: 1.0
Name: nose-connection-report
Version: 0.2
Summary: Nose testing framework plugin for monitoring network connections
Home-page: http://github.com/ustudio/nose_connection_report/
Author: Thomas Stephens, John J. Lee, Dan McCombs
Author-email: thomas@ustudio.com
License: BSD
Platform: any
